jilutil/__init__.py
jilutil/__main__.py
jilutil/auto_sys_job.py
jilutil/jil_parser.py
jilutil-0.3.0.dist-info/LICENSE
jilutil-0.3.0.dist-info/METADATA
jilutil-0.3.0.dist-info/WHEEL
jilutil-0.3.0.dist-info/top_level.txt
jilutil-0.3.0.dist-info/RECORD
