Metadata-Version: 2.1
Name: jilutil
Version: 0.3.0
License: MIT License
Requires-Python: >=3.9
License-File: LICENSE
Provides-Extra: dev
Requires-Dist: pytest; extra == "dev"
Requires-Dist: build; extra == "dev"
Requires-Dist: twine>=4.0.2; extra == "dev"
Requires-Dist: pytest>=7.4; extra == "dev"
Requires-Dist: pytest-cov>=4.1; extra == "dev"
Requires-Dist: pytest-sugar>=0.9.7; extra == "dev"
Requires-Dist: ruff>=0.1.0; extra == "dev"
Requires-Dist: pre-commit>=3.6.0; python_version >= "3.9" and extra == "dev"
Requires-Dist: detect-secrets>=1.4.0; extra == "dev"
